fastapi_mcp/__init__.py
fastapi_mcp/server.py
fastapi_mcp/types.py
fastapi_mcp/auth/__init__.py
fastapi_mcp/auth/proxy.py
fastapi_mcp/openapi/__init__.py
fastapi_mcp/openapi/convert.py
fastapi_mcp/openapi/utils.py
fastapi_mcp/transport/__init__.py
fastapi_mcp/transport/http.py
fastapi_mcp/transport/sse.py
fastapi_mcp/utils/__init__.py
mseep_fastapi_mcp-0.4.1.dist-info/METADATA
mseep_fastapi_mcp-0.4.1.dist-info/WHEEL
mseep_fastapi_mcp-0.4.1.dist-info/licenses/LICENSE
mseep_fastapi_mcp-0.4.1.dist-info/RECORD
