Metadata-Version: 2.4
Name: mseep-fastapi-mcp
Version: 0.4.1
Summary: Automatic MCP server generator for FastAPI applications - converts FastAPI endpoints to MCP tools for LLM integration
Project-URL: Homepage, https://github.com/tadata-org/fastapi_mcp
Project-URL: Documentation, https://github.com/tadata-org/fastapi_mcp#readme
Project-URL: Bug Tracker, https://github.com/tadata-org/fastapi_mcp/issues
Project-URL: PyPI, https://pypi.org/project/fastapi-mcp/
Project-URL: Source Code, https://github.com/tadata-org/fastapi_mcp
Project-URL: Changelog, https://github.com/tadata-org/fastapi_mcp/blob/main/CHANGELOG.md
Author-email: mseep <support@skydeck.ai>
License: MIT License
License-File: LICENSE
Keywords: ai,api,claude,conversion,fastapi,llm,mcp,modelcontextprotocol,openapi,tools
Classifier: Development Status :: 3 - Alpha
Classifier: Framework :: FastAPI
Classifier: Intended Audience :: Developers
Classifier: License :: OSI Approved :: MIT License
Classifier: Programming Language :: Python :: 3
Classifier: Programming Language :: Python :: 3.10
Classifier: Programming Language :: Python :: 3.11
Classifier: Programming Language :: Python :: 3.12
Classifier: Topic :: Internet :: WWW/HTTP
Classifier: Topic :: Software Development :: Libraries :: Python Modules
Requires-Python: >=3.10
Requires-Dist: fastapi>=0.100.0
Requires-Dist: httpx>=0.24.0
Requires-Dist: mcp>=1.12.0
Requires-Dist: pydantic-settings>=2.5.2
Requires-Dist: pydantic>=2.0.0
Requires-Dist: requests>=2.25.0
Requires-Dist: rich>=13.0.0
Requires-Dist: tomli>=2.2.1
Requires-Dist: typer>=0.9.0
Requires-Dist: uvicorn>=0.20.0
